pystrong/__init__.py
pystrong/checker.py
pystrong/constants.py
pystrong/decorators.py
pystrong/enforcer.py
pystrong/exceptions.py
PyStrong-0.0.7.dist-info/METADATA
PyStrong-0.0.7.dist-info/WHEEL
PyStrong-0.0.7.dist-info/top_level.txt
PyStrong-0.0.7.dist-info/RECORD
