Metadata-Version: 2.1
Name: PyStrong
Version: 0.0.7
Summary: Type enforcement for python objects.
Home-page: https://github.com/hyptocrypto/Pystrong
Author: Julian Baumgartner
Author-email: jbaumgartner93@gmail.com
License: UNKNOWN
Project-URL: Bug Tracker, https://github.com/hyptocrypto/Pystrong/issues
Platform: UNKNOWN
Classifier: Programming Language :: Python :: 3
Classifier: License :: OSI Approved :: MIT License
Classifier: Operating System :: OS Independent
Requires-Python: >=3.6
